README.md
setup.py
tqdmX/__init__.py
tqdmX/core.py
tqdmX.egg-info/PKG-INFO
tqdmX.egg-info/SOURCES.txt
tqdmX.egg-info/dependency_links.txt
tqdmX.egg-info/requires.txt
tqdmX.egg-info/top_level.txt