Metadata-Version: 2.1
Name: tqdmX
Version: 0.0.4
Summary: A tqdm wrapper for multi-line logging.
Home-page: https://github.com/kimythanly/tqdmX
Author: KimythAnly
Author-email: kimythanly@gmail.com
License: UNKNOWN
Platform: UNKNOWN
Classifier: Programming Language :: Python :: 3
Classifier: License :: OSI Approved :: MIT License
Classifier: Operating System :: OS Independent
Requires-Python: >=3.6
